comicpy/__init__.py
comicpy/__main__.py
comicpy/bin_rar/rar
comicpy/bin_rar/unrar
comicpy/bin_rar/version_rar.txt
comicpy/checkfile.py
comicpy/cli.py
comicpy/comicpycontroller.py
comicpy/exceptionsClasses.py
comicpy/filesigns.py
comicpy/handlers/__init__.py
comicpy/handlers/baseziprar.py
comicpy/handlers/directoryhandler.py
comicpy/handlers/imageshandler.py
comicpy/handlers/pdfhandler.py
comicpy/handlers/pdfhandler_thread.py
comicpy/handlers/rarhandler.py
comicpy/handlers/ziphandler.py
comicpy/models.py
comicpy/utils.py
comicpy/valid_extensions.py
comicpy/version.py
comicpy-0.1.41.dist-info/METADATA
comicpy-0.1.41.dist-info/WHEEL
comicpy-0.1.41.dist-info/entry_points.txt
comicpy-0.1.41.dist-info/RECORD
