Metadata-Version: 2.3
Name: comicpy
Version: 0.1.41
Summary: Tool to create CBR or CBZ files, supports PDF, ZIP, RAR files.
License: MIT
Keywords: comic,cbz,cbr,manga
Author: kurotom
Author-email: 55354389+kurotom@users.noreply.github.com
Requires-Python: >=3.9,<4.0
Classifier: License :: OSI Approved :: MIT License
Classifier: Operating System :: OS Independent
Classifier: Programming Language :: Python :: 3
Classifier: Programming Language :: Python :: 3.9
Classifier: Programming Language :: Python :: 3.10
Classifier: Programming Language :: Python :: 3.11
Classifier: Programming Language :: Python :: 3.12
Classifier: Programming Language :: Python :: 3.13
Requires-Dist: pillow (>=11,<12)
Requires-Dist: pycryptodome (>=3.20.0,<4.0.0)
Requires-Dist: pymupdf (==1.25.3)
Requires-Dist: pyzipper (>=0.3.6,<0.4.0)
Requires-Dist: rarfile (>=4.1,<5.0)
Project-URL: Bug Tracker, https://github.com/kurotom/comicpy/issues
Project-URL: Repository, https://github.com/kurotom/comicpy
